LICENSE.md
MANIFEST.in
README.rst
setup.py
src/nodeconductor_auth_social/__init__.py
src/nodeconductor_auth_social/apps.py
src/nodeconductor_auth_social/extension.py
src/nodeconductor_auth_social/handlers.py
src/nodeconductor_auth_social/models.py
src/nodeconductor_auth_social/serializers.py
src/nodeconductor_auth_social/tasks.py
src/nodeconductor_auth_social/urls.py
src/nodeconductor_auth_social/views.py
src/nodeconductor_auth_social.egg-info/PKG-INFO
src/nodeconductor_auth_social.egg-info/SOURCES.txt
src/nodeconductor_auth_social.egg-info/dependency_links.txt
src/nodeconductor_auth_social.egg-info/entry_points.txt
src/nodeconductor_auth_social.egg-info/not-zip-safe
src/nodeconductor_auth_social.egg-info/requires.txt
src/nodeconductor_auth_social.egg-info/top_level.txt
src/nodeconductor_auth_social/migrations/0001_initial.py
src/nodeconductor_auth_social/migrations/__init__.py
src/nodeconductor_auth_social/templates/nodeconductor_auth_social/activation_email_body.txt