Metadata-Version: 1.1
Name: nodeconductor-auth-social
Version: 0.5.0
Summary: NodeConductor plugin for authentication with social networks such as Facebook, Google Plus.
Home-page: http://nodeconductor.com
Author: OpenNode Team
Author-email: info@opennodecloud.com
License: UNKNOWN
Platform: UNKNOWN
Classifier: Framework :: Django
Classifier: Intended Audience :: Developers
Classifier: Intended Audience :: System Administrators
Classifier: License :: OSI Approved :: MIT License
Classifier: Operating System :: OS Independent
